hotspots/__init__.py
hotspots/hotspots.py
trajectory_hotspots-0.1.4.dist-info/METADATA
trajectory_hotspots-0.1.4.dist-info/WHEEL
trajectory_hotspots-0.1.4.dist-info/top_level.txt
trajectory_hotspots-0.1.4.dist-info/RECORD
