Metadata-Version: 2.1
Name: trajectory-hotspots
Version: 0.1.4
Summary: A Python library to detect hotspots between two trajectories
Home-page: https://github.com/22IMED/trajectory-hotspots
Author: Imed Eddine ZEROUAL
Author-email: imededdinezeroual@gmail.com
License: UNKNOWN
Platform: UNKNOWN
Classifier: Programming Language :: Python :: 3
Classifier: License :: OSI Approved :: MIT License
Classifier: Operating System :: OS Independent
Requires-Python: >=3.6
Requires-Dist: geopy
